TCsorgu/__init__.py
TCsorgu-0.3.data/scripts/TCsorgu
TCsorgu-0.3.dist-info/LICENSE
TCsorgu-0.3.dist-info/METADATA
TCsorgu-0.3.dist-info/WHEEL
TCsorgu-0.3.dist-info/top_level.txt
TCsorgu-0.3.dist-info/RECORD
