Metadata-Version: 2.1
Name: TCsorgu
Version: 0.3
Summary: Checks tckimlik.nvi.gov.tr
Home-page: http://github.com/dorukgezici/TCsorgu
Author: Doruk Gezici
Author-email: dorukgezici@gmail.com
License: MIT
Platform: UNKNOWN
Classifier: Programming Language :: Python :: 3
Classifier: License :: OSI Approved :: MIT License
Classifier: Operating System :: OS Independent
Requires-Dist: requests
